{
  "config": {
    "num_episodes": 1000,
    "max_steps_per_episode": 500,
    "seed": 249989,
    "verbose": false,
    "learning_rate": 0.00027192247149031306,
    "epsilon_start": 0.5,
    "epsilon_decay": 0.9999,
    "epsilon_min": 0.1,
    "batch_size": 64,
    "buffer_size": 100000,
    "gamma": 0.99,
    "target_update_freq": 5,
    "config_id": "cfg_batch_size=64_buffer_size=100000_epsilon_decay=0.9999_epsilon_min=0.1_epsilon_start=0.5_gamma=0.99_learning_rate=0.00027192247149031306_target_update_freq=5",
    "rep_index": 25
  },
  "mean_reward": -297.415,
  "std_reward": 26.67472164803224
}